jarvismode/version/__init__.py
jarvismode/version/version.py
jarvismode-1.0.70.dist-info/METADATA
jarvismode-1.0.70.dist-info/WHEEL
jarvismode-1.0.70.dist-info/entry_points.txt
jarvismode-1.0.70.dist-info/licenses/LICENSE
jarvismode-1.0.70.dist-info/RECORD
